odoo10_addon_account_analytic_default_account-10.0.1.0.0-py2.7-nspkg.pth
odoo/addons/account_analytic_default_account/README.rst
odoo/addons/account_analytic_default_account/__init__.py
odoo/addons/account_analytic_default_account/__manifest__.py
odoo/addons/account_analytic_default_account/models/__init__.py
odoo/addons/account_analytic_default_account/models/account_analytic_default_account.py
odoo/addons/account_analytic_default_account/tests/__init__.py
odoo/addons/account_analytic_default_account/tests/test_analytic_default_account.py
odoo/addons/account_analytic_default_account/views/account_analytic_default_account_view.xml
odoo10_addon_account_analytic_default_account-10.0.1.0.0.dist-info/DESCRIPTION.rst
odoo10_addon_account_analytic_default_account-10.0.1.0.0.dist-info/METADATA
odoo10_addon_account_analytic_default_account-10.0.1.0.0.dist-info/RECORD
odoo10_addon_account_analytic_default_account-10.0.1.0.0.dist-info/WHEEL
odoo10_addon_account_analytic_default_account-10.0.1.0.0.dist-info/metadata.json
odoo10_addon_account_analytic_default_account-10.0.1.0.0.dist-info/namespace_packages.txt
odoo10_addon_account_analytic_default_account-10.0.1.0.0.dist-info/top_level.txt
