Metadata-Version: 2.0
Name: odoo10-addon-account-analytic-default-account
Version: 10.0.1.0.0
Summary: Account Analytic Default Account
Home-page: https://github.com/OCA/account-analytic
Author: Odoo Community Association (OCA)
Author-email: support@odoo-community.org
License: AGPL-3
Platform: UNKNOWN
Classifier: Programming Language :: Python
Classifier: Framework :: Odoo
Classifier: License :: OSI Approved :: GNU Affero General Public License v3
Requires-Python: ~=2.7
Requires-Dist: odoo (<10.1dev,>=10.0)
